<?xml version="1.0" encoding="UTF-8" standalone="no"?>
<recordset table="format">
  <record id="syslanguage=&quot;en&quot; and name=&quot;sap.sold.to.party&quot;" recordid="en - sap.sold.to.party">
    <name mandatory="true" type="string">sap.sold.to.party</name>
    <field sctype="array">
      <field sctype="structure">
        <flags type="decimal">0</flags>
        <line type="decimal">1</line>
        <column type="decimal">3</column>
        <length type="decimal">20</length>
        <window type="decimal">0</window>
        <attribute type="decimal">2</attribute>
        <graph sctype="array"/>
        <input NullValue="1" type="string"/>
        <output type="string">City:</output>
        <format NullValue="1" type="string"/>
        <property type="string">Label;Caption=City:	X=4	Y=0	Height=2	Width=40	ForeColor=0	</property>
      </field>
      <field sctype="structure">
        <flags type="decimal">0</flags>
        <line type="decimal">1</line>
        <column type="decimal">25</column>
        <length type="decimal">40</length>
        <window type="decimal">0</window>
        <attribute type="decimal">1</attribute>
        <graph sctype="array"/>
        <input type="string">city</input>
        <output NullValue="1" type="string"/>
        <format NullValue="1" type="string"/>
        <property type="string">Text;Input=city	X=48	Y=0	Height=2	Width=80	</property>
      </field>
      <field sctype="structure">
        <flags type="decimal">0</flags>
        <line type="decimal">2</line>
        <column type="decimal">3</column>
        <length type="decimal">20</length>
        <window type="decimal">0</window>
        <attribute type="decimal">2</attribute>
        <graph sctype="array"/>
        <input NullValue="1" type="string"/>
        <output type="string">Client:</output>
        <format NullValue="1" type="string"/>
        <property type="string">Label;Caption=Client:	X=4	Y=2	Height=2	Width=40	ForeColor=0	</property>
      </field>
      <field sctype="structure">
        <flags type="decimal">0</flags>
        <line type="decimal">2</line>
        <column type="decimal">25</column>
        <length type="decimal">40</length>
        <window type="decimal">0</window>
        <attribute type="decimal">1</attribute>
        <graph sctype="array"/>
        <input type="string">client</input>
        <output NullValue="1" type="string"/>
        <format NullValue="1" type="string"/>
        <property type="string">Text;Input=client	X=48	Y=2	Height=2	Width=80	</property>
      </field>
      <field sctype="structure">
        <flags type="decimal">0</flags>
        <line type="decimal">3</line>
        <column type="decimal">3</column>
        <length type="decimal">20</length>
        <window type="decimal">0</window>
        <attribute type="decimal">2</attribute>
        <graph sctype="array"/>
        <input NullValue="1" type="string"/>
        <output type="string">Customer Number:</output>
        <format NullValue="1" type="string"/>
        <property type="string">Label;Caption=Customer Number:	X=4	Y=4	Height=2	Width=40	ForeColor=0	</property>
      </field>
      <field sctype="structure">
        <flags type="decimal">0</flags>
        <line type="decimal">3</line>
        <column type="decimal">25</column>
        <length type="decimal">40</length>
        <window type="decimal">0</window>
        <attribute type="decimal">1</attribute>
        <graph sctype="array"/>
        <input type="string">customer.number</input>
        <output NullValue="1" type="string"/>
        <format NullValue="1" type="string"/>
        <property type="string">Text;Input=customer.number	X=48	Y=4	Height=2	Width=80	</property>
      </field>
      <field sctype="structure">
        <flags type="decimal">0</flags>
        <line type="decimal">4</line>
        <column type="decimal">3</column>
        <length type="decimal">20</length>
        <window type="decimal">0</window>
        <attribute type="decimal">2</attribute>
        <graph sctype="array"/>
        <input NullValue="1" type="string"/>
        <output type="string">Name:</output>
        <format NullValue="1" type="string"/>
        <property type="string">Label;Caption=Name:	X=4	Y=6	Height=2	Width=40	ForeColor=0	</property>
      </field>
      <field sctype="structure">
        <flags type="decimal">0</flags>
        <line type="decimal">4</line>
        <column type="decimal">25</column>
        <length type="decimal">40</length>
        <window type="decimal">0</window>
        <attribute type="decimal">1</attribute>
        <graph sctype="array"/>
        <input type="string">name</input>
        <output NullValue="1" type="string"/>
        <format NullValue="1" type="string"/>
        <property type="string">Text;Input=name	X=48	Y=6	Height=2	Width=80	</property>
      </field>
      <field sctype="structure">
        <flags type="decimal">0</flags>
        <line type="decimal">5</line>
        <column type="decimal">3</column>
        <length type="decimal">20</length>
        <window type="decimal">0</window>
        <attribute type="decimal">2</attribute>
        <graph sctype="array"/>
        <input NullValue="1" type="string"/>
        <output type="string">Postal Code:</output>
        <format NullValue="1" type="string"/>
        <property type="string">Label;Caption=Postal Code:	X=4	Y=8	Height=2	Width=40	ForeColor=0	</property>
      </field>
      <field sctype="structure">
        <flags type="decimal">0</flags>
        <line type="decimal">5</line>
        <column type="decimal">25</column>
        <length type="decimal">40</length>
        <window type="decimal">0</window>
        <attribute type="decimal">1</attribute>
        <graph sctype="array"/>
        <input type="string">postal.code</input>
        <output NullValue="1" type="string"/>
        <format NullValue="1" type="string"/>
        <property type="string">Text;Input=postal.code	X=48	Y=8	Height=2	Width=80	</property>
      </field>
      <field sctype="structure">
        <flags type="decimal">0</flags>
        <line type="decimal">6</line>
        <column type="decimal">3</column>
        <length type="decimal">20</length>
        <window type="decimal">0</window>
        <attribute type="decimal">2</attribute>
        <graph sctype="array"/>
        <input NullValue="1" type="string"/>
        <output type="string">Sort Field:</output>
        <format NullValue="1" type="string"/>
        <property type="string">Label;Caption=Sort Field:	X=4	Height=2	Width=40	ForeColor=0	</property>
      </field>
      <field sctype="structure">
        <flags type="decimal">0</flags>
        <line type="decimal">6</line>
        <column type="decimal">25</column>
        <length type="decimal">40</length>
        <window type="decimal">0</window>
        <attribute type="decimal">1</attribute>
        <graph sctype="array"/>
        <input type="string">sort.field</input>
        <output NullValue="1" type="string"/>
        <format NullValue="1" type="string"/>
        <property type="string">Text;Input=sort.field	X=48	Height=2	Width=80	</property>
      </field>
    </field>
    <file.name type="string">sapsoldtoparty</file.name>
    <editor type="string">lisa</editor>
    <last.update type="dateTime">05/25/99 04:29:26</last.update>
    <help.topic NullValue="1" type="string"/>
    <syslanguage type="string">en</syslanguage>
    <sysmodcount type="decimal">11</sysmodcount>
    <sysmoduser type="string">falcon</sysmoduser>
    <sysmodtime type="dateTime">10/24/01 08:17:31</sysmodtime>
    <description NullValue="1" type="string"/>
  </record>
</recordset>
